goby_sdk/__init__.py
goby_sdk/version.py
goby_sdk/V1/__init__.py
goby_sdk/V1/api.py
goby_sdk/V1/lib/__init__.py
goby_sdk/V1/lib/asset_page.py
goby_sdk/V1/lib/base_page.py
goby_sdk/V1/lib/config_page.py
goby_sdk/V1/lib/home_page.py
goby_sdk/V1/lib/report_page.py
goby_sdk/V1/lib/vulnerability_management_page.py
goby_sdk-1.0.9.dist-info/METADATA
goby_sdk-1.0.9.dist-info/WHEEL
goby_sdk-1.0.9.dist-info/top_level.txt
goby_sdk-1.0.9.dist-info/RECORD
