Metadata-Version: 2.1
Name: goby-sdk
Version: 1.0.9
Summary: A Python SDK for Goby, Visit for details: https://www.exp-9.com/category-20.html
Home-page: https://github.com/siberiah0h/goby_sdk_for_python
Author: siberia
Author-email: siberiah0h@gmail.com
Requires-Dist: requests (>=2.25.1)
